<annotation>
	<folder></folder>
	<filename>probe_49_png.rf.hCIlAXNurh2GSFaYNE1q.png</filename>
	<path>probe_49_png.rf.hCIlAXNurh2GSFaYNE1q.png</path>
	<source>
		<database>roboflow.com</database>
	</source>
	<size>
		<width>1280</width>
		<height>720</height>
		<depth>3</depth>
	</size>
	<segmented>0</segmented>
	<object>
		<name>probe</name>
		<pose>Unspecified</pose>
		<truncated>0</truncated>
		<difficult>0</difficult>
		<occluded>0</occluded>
		<bndbox>
			<xmin>1090</xmin>
			<xmax>NaN</xmax>
			<ymin>68</ymin>
			<ymax>NaN</ymax>
		</bndbox>
		<polygon>
			<x1>1109.839</x1>
			<y1>67.916</y1>
			<x2>1127.897</x2>
			<y2>68.455</y2>
			<x3>1099.868</x3>
			<y3>190.274</y3>
			<x4>1088.818</x4>
			<y4>185.961</y4>
			<x5>1103.371</x5>
			<y5>66.838</y5>
		</polygon>
	</object>
	<metadata>
		<tags>
			<tag>afternoon</tag>
		</tags>
	</metadata>
</annotation>
