<annotation>
	<folder></folder>
	<filename>probe_310_png.rf.PgxRTGzxutAIVspxLLRP.png</filename>
	<path>probe_310_png.rf.PgxRTGzxutAIVspxLLRP.png</path>
	<source>
		<database>roboflow.com</database>
	</source>
	<size>
		<width>1280</width>
		<height>720</height>
		<depth>3</depth>
	</size>
	<segmented>0</segmented>
	<object>
		<name>probe</name>
		<pose>Unspecified</pose>
		<truncated>0</truncated>
		<difficult>0</difficult>
		<occluded>0</occluded>
		<bndbox>
			<xmin>823</xmin>
			<xmax>NaN</xmax>
			<ymin>209</ymin>
			<ymax>NaN</ymax>
		</bndbox>
		<polygon>
			<x1>823.14</x1>
			<y1>219.32</y1>
			<x2>840.879</x2>
			<y2>207.57</y2>
			<x3>899.625</x3>
			<y3>304.099</y3>
			<x4>892.022</x4>
			<y4>310.78</y4>
			<x5>822.218</x5>
			<y5>219.78</y5>
		</polygon>
	</object>
	<metadata>
		<tags>
			<tag>afternoon</tag>
		</tags>
	</metadata>
</annotation>
